tests
balog
