Metadata-Version: 1.0
Name: balog
Version: 1.2.1
Summary: Balanced event logging schema and library
Home-page: https://github.com/balanced/balog/
Author: Balanced
Author-email: dev@balancedpayments.com
License: UNKNOWN
Platform: UNKNOWN
